CHANGELOG.rst
MANIFEST.in
README.rst
setup.py
echarts_themes_pypkg/__init__.py
echarts_themes_pypkg/_version.py
echarts_themes_pypkg.egg-info/PKG-INFO
echarts_themes_pypkg.egg-info/SOURCES.txt
echarts_themes_pypkg.egg-info/dependency_links.txt
echarts_themes_pypkg.egg-info/not-zip-safe
echarts_themes_pypkg.egg-info/requires.txt
echarts_themes_pypkg.egg-info/top_level.txt
echarts_themes_pypkg/resources/registry.json
echarts_themes_pypkg/resources/echarts-themes-js/chalk.js
echarts_themes_pypkg/resources/echarts-themes-js/essos.js
echarts_themes_pypkg/resources/echarts-themes-js/halloween.js
echarts_themes_pypkg/resources/echarts-themes-js/index.js
echarts_themes_pypkg/resources/echarts-themes-js/infographic.js
echarts_themes_pypkg/resources/echarts-themes-js/macarons.js
echarts_themes_pypkg/resources/echarts-themes-js/purple-passion.js
echarts_themes_pypkg/resources/echarts-themes-js/roma.js
echarts_themes_pypkg/resources/echarts-themes-js/shine.js
echarts_themes_pypkg/resources/echarts-themes-js/vintage.js
echarts_themes_pypkg/resources/echarts-themes-js/walden.js
echarts_themes_pypkg/resources/echarts-themes-js/westeros.js
echarts_themes_pypkg/resources/echarts-themes-js/wonderland.js