Metadata-Version: 1.1
Name: echarts-themes-pypkg
Version: 0.0.2
Summary: packages echarts vintage, macarons, infographic, shine, roma themes
Home-page: https://github.com/pyecharts/echarts-themes-pypkg
Author: C.W.
Author-email: wangc_2011@hotmail.com
License: git push -u origin masterMIT
Download-URL: https://github.com/pyecharts/echarts-themes-pypkg/archive/0.0.2.tar.gz
Keywords: python
Platform: UNKNOWN
Classifier: Topic :: Office/Business
Classifier: Topic :: Utilities
Classifier: Topic :: Software Development :: Libraries
Classifier: Programming Language :: Python
Classifier: Intended Audience :: Developers
Classifier: Programming Language :: Python :: 2.6
Classifier: Programming Language :: Python :: 2.7
Classifier: Programming Language :: Python :: 3.3
Classifier: Programming Language :: Python :: 3.4
Classifier: Programming Language :: Python :: 3.5
Classifier: Programming Language :: Python :: 3.6
